easedb/__init__.py
easedb/async_base.py
easedb/base.py
easedb/cli/commands.py
easedb/cli/docker.py
easedb/cli/main.py
easedb/cli/utils.py
easedb/cli/platforms/__init__.py
easedb/cli/platforms/common/docker_utils.py
easedb/cli/platforms/linux/__init__.py
easedb/cli/platforms/linux/docker_install.py
easedb/cli/platforms/mac/__init__.py
easedb/cli/platforms/mac/docker_install.py
easedb/cli/platforms/windows/__init__.py
easedb/cli/platforms/windows/docker_install.py
easedb/cli/platforms/windows/operations/__init__.py
easedb/cli/platforms/windows/operations/chocolatey.py
easedb/cli/platforms/windows/operations/manual.py
easedb/cli/platforms/windows/operations/uninstall.py
easedb/core/database.py
easedb/drivers/base/__init__.py
easedb/drivers/base/aio.py
easedb/drivers/base/sync.py
easedb/drivers/base/aio/connect.py
easedb/drivers/base/aio/disconnect.py
easedb/drivers/mysql/__init__.py
easedb/drivers/mysql/utils.py
easedb/drivers/mysql/aio/__init__.py
easedb/drivers/mysql/aio/add.py
easedb/drivers/mysql/aio/create_table.py
easedb/drivers/mysql/aio/delete.py
easedb/drivers/mysql/aio/execute.py
easedb/drivers/mysql/aio/get.py
easedb/drivers/mysql/aio/get_all.py
easedb/drivers/mysql/aio/set.py
easedb/drivers/mysql/aio/sub.py
easedb/drivers/mysql/aio/update.py
easedb/drivers/mysql/sync/__init__.py
easedb/drivers/mysql/sync/create_table.py
easedb/drivers/mysql/sync/delete.py
easedb/drivers/mysql/sync/execute.py
easedb/drivers/mysql/sync/get.py
easedb/drivers/mysql/sync/get_all.py
easedb/drivers/mysql/sync/set.py
easedb/drivers/mysql/sync/update.py
easedb/drivers/sqlite/__init__.py
easedb/drivers/sqlite/utils.py
easedb/drivers/sqlite/aio/__init__.py
easedb/drivers/sqlite/aio/count.py
easedb/drivers/sqlite/aio/create_table.py
easedb/drivers/sqlite/aio/delete.py
easedb/drivers/sqlite/aio/execute.py
easedb/drivers/sqlite/aio/get.py
easedb/drivers/sqlite/aio/get_all.py
easedb/drivers/sqlite/aio/set.py
easedb/drivers/sqlite/aio/update.py
easedb/drivers/sqlite/sync/__init__.py
easedb-0.1.5.dist-info/METADATA
easedb-0.1.5.dist-info/WHEEL
easedb-0.1.5.dist-info/entry_points.txt
easedb-0.1.5.dist-info/top_level.txt
easedb-0.1.5.dist-info/RECORD
