Metadata-Version: 2.4
Name: easedb
Version: 0.1.5
Summary: Fast, simple, reliable — Database management made easy
Author: Boylair <boylair@tuta.io>
Project-URL: Homepage, https://github.com/Boylair/easedb
Project-URL: Bug Tracker, https://github.com/Boylair/easedb/issues
Classifier: Programming Language :: Python :: 3
Classifier: License :: OSI Approved :: MIT License
Classifier: Operating System :: OS Independent
Requires-Python: >=3.7
Requires-Dist: aiomysql==0.2.0
Requires-Dist: mysql-connector-python>=9.1.0
Requires-Dist: aiosqlite>=0.19.0
Requires-Dist: asyncio>=3.4.3
Requires-Dist: typing-extensions>=4.0.0
Requires-Dist: loguru>=0.7.3
Provides-Extra: mysql
Requires-Dist: aiomysql==0.2.0; extra == "mysql"
Requires-Dist: mysql-connector-python>=9.1.0; extra == "mysql"
Requires-Dist: asyncio>=3.4.3; extra == "mysql"
Requires-Dist: typing-extensions>=4.0.0; extra == "mysql"
Provides-Extra: sqlite
Requires-Dist: aiosqlite>=0.19.0; extra == "sqlite"
Requires-Dist: asyncio>=3.4.3; extra == "sqlite"
Requires-Dist: typing-extensions>=4.0.0; extra == "sqlite"
Provides-Extra: dev
Requires-Dist: pytest==7.4.3; extra == "dev"
Requires-Dist: pytest-asyncio==0.21.1; extra == "dev"
Requires-Dist: pytest-cov>=3.0.0; extra == "dev"
Requires-Dist: coverage>=6.0.0; extra == "dev"
Provides-Extra: all
Requires-Dist: aiomysql==0.2.0; extra == "all"
Requires-Dist: mysql-connector-python>=9.1.0; extra == "all"
Requires-Dist: aiosqlite>=0.19.0; extra == "all"
Requires-Dist: asyncio>=3.4.3; extra == "all"
Requires-Dist: typing-extensions>=4.0.0; extra == "all"
Requires-Dist: coverage>=6.0.0; extra == "all"
